STRINGdb/__init__.py
STRINGdb/graph.py
STRINGdb/network.py
STRINGdb/prep.py
STRINGdb/version.py
STRINGdb/dataset/genes.csv
py_STRINGdb-0.3.0.dist-info/LICENSE
py_STRINGdb-0.3.0.dist-info/METADATA
py_STRINGdb-0.3.0.dist-info/WHEEL
py_STRINGdb-0.3.0.dist-info/entry_points.txt
py_STRINGdb-0.3.0.dist-info/top_level.txt
py_STRINGdb-0.3.0.dist-info/RECORD
