Metadata-Version: 2.1
Name: py-STRINGdb
Version: 0.3.0
Summary: STRINGdb python REST api
Author-email: Rongbo Wu <wurongbo2012@hotmail.com>
Project-URL: Homepage, https://github.com/wrb2012/string-db/
Requires-Python: >=3.8
License-File: LICENSE
Requires-Dist: httpx >=0.21
Requires-Dist: pandas >=1.4
Requires-Dist: igraph >0.11.0
Requires-Dist: matplotlib >=3.3
